[{"name":"你就不要想起我","type":"local","author":"Npc","filename":"你就不要想起我-C哥.mp3","id":"2032038447422"},{"name":"虎口脱险 (Live)","type":"local","author":"张磊","filename":"张磊 - 虎口脱险 (live).mp3","id":"243527642651"},{"name":"忠贞","type":"local","author":"Npc","filename":"忠贞.mp3","id":"2454422596321"},{"name":"长镜头 (Live);长镜头","type":"local","author":"杨宗纬;杨宗纬","filename":"长镜头 (Live).mp3","id":"3827185486597"},{"name":"关于郑州的记忆","type":"local","author":"李志","filename":"关于郑州的记忆.mp3","id":"208513911527"},{"name":"这个世界会好吗 (相信未来版)","type":"local","author":"李志","filename":"这个世界会好吗 (相信未来版) - 李志.mp3","id":"3682577310925"},{"name":"黑色信封","type":"local","author":"李志","filename":"李志 - 黑色信封.mp3","id":"2644614051573"}]